os2mo_fastapi_utils/__init__.py
os2mo_fastapi_utils/auth/__init__.py
os2mo_fastapi_utils/auth/exceptions.py
os2mo_fastapi_utils/auth/models.py
os2mo_fastapi_utils/auth/oidc.py
os2mo_fastapi_utils/auth/test_helper.py
os2mo_fastapi_utils/py.typed
os2mo_fastapi_utils/pydantic_types.py
os2mo_fastapi_utils/tracing.py
os2mo_fastapi_utils-1.3.4.dist-info/LICENSE
os2mo_fastapi_utils-1.3.4.dist-info/LICENSES/MPL-2.0.txt
os2mo_fastapi_utils-1.3.4.dist-info/METADATA
os2mo_fastapi_utils-1.3.4.dist-info/WHEEL
os2mo_fastapi_utils-1.3.4.dist-info/RECORD
