Metadata-Version: 2.1
Name: os2mo-fastapi-utils
Version: 1.3.4
Summary: FastAPI utils for os2mo
Home-page: https://magenta.dk/
License: MPL-2.0
Keywords: os2mo-fastapi-utils,os2mo,fastapi,utils
Author: Magenta
Author-email: info@magenta.dk
Requires-Python: >=3.10,<4.0
Classifier: License :: OSI Approved
Classifier: Programming Language :: Python :: 3
Classifier: Programming Language :: Python :: 3.10
Classifier: Programming Language :: Python :: 3.11
Requires-Dist: aiohttp (>=3,<4)
Requires-Dist: fastapi (>=0.85,<1)
Requires-Dist: httpx (>=0.19,<1)
Requires-Dist: opentelemetry-api (>=1.18,<2)
Requires-Dist: opentelemetry-exporter-jaeger (>=1.18,<2)
Requires-Dist: opentelemetry-instrumentation-aiohttp-client (>=0.39b0,<1)
Requires-Dist: opentelemetry-instrumentation-fastapi (>=0.39b0,<1)
Requires-Dist: opentelemetry-instrumentation-httpx (>=0.39b0,<1)
Requires-Dist: opentelemetry-instrumentation-requests (>=0.39b0,<1)
Requires-Dist: opentelemetry-sdk (>=1.18,<2)
Requires-Dist: pydantic[email] (>=1.10,<2)
Requires-Dist: pyjwt[crypto] (>=2.7,<3)
Requires-Dist: requests (>=2,<3)
Requires-Dist: structlog (>=22.1)
Project-URL: Repository, https://git.magenta.dk/rammearkitektur/os2mo-fastapi-utils
